piano/__init__.py
piano/__main__.py
piano/models/__init__.py
piano/models/base_models.py
piano/models/base_modules.py
piano/utils/__init__.py
piano/utils/composer.py
piano/utils/covariates.py
piano/utils/data.py
piano/utils/preprocessing.py
piano/utils/timer.py
piano/utils/triton_sparse.py
piano_integration-0.1.0.dist-info/licenses/LICENSE
piano_integration-0.1.0.dist-info/METADATA
piano_integration-0.1.0.dist-info/WHEEL
piano_integration-0.1.0.dist-info/top_level.txt
piano_integration-0.1.0.dist-info/RECORD
