Metadata-Version: 2.4
Name: piano-integration
Version: 0.1.0
Summary: PIANO: Probabilistic Inference Autoencoder Networks for multi-Omics
Home-page: https://github.com/ningwang1729/piano
Author: Ning Wang
Author-email: Ning Wang <nw8333@princeton.edu>
License-Expression: GPL-3.0-or-later
Classifier: Programming Language :: Python
Classifier: Operating System :: OS Independent
Requires-Python: >=3.11.14
License-File: LICENSE
Requires-Dist: fast-array-utils
Requires-Dist: matplotlib
Requires-Dist: numpy>=2
Requires-Dist: pandas
Requires-Dist: scipy
Requires-Dist: scikit-misc
Requires-Dist: anndata
Requires-Dist: scanpy
Requires-Dist: torch<2.8,>=2.2
Requires-Dist: pyro-ppl
Provides-Extra: rapids
Requires-Dist: torch<2.8,>=2.2; extra == "rapids"
Requires-Dist: rapids-singlecell[rapids12]==0.13.1; extra == "rapids"
Provides-Extra: scvi-tools
Requires-Dist: torch<2.8,>=2.2; extra == "scvi-tools"
Requires-Dist: jax[cuda12]; extra == "scvi-tools"
Requires-Dist: scvi-tools; extra == "scvi-tools"
Requires-Dist: chex<=0.1.91; extra == "scvi-tools"
Requires-Dist: scib-metrics==0.5.3; extra == "scvi-tools"
Provides-Extra: torch
Requires-Dist: torch<2.8,>=2.2; extra == "torch"
Requires-Dist: torchvision; extra == "torch"
Requires-Dist: torchaudio; extra == "torch"
Provides-Extra: misc
Requires-Dist: torch<2.8,>=2.2; extra == "misc"
Requires-Dist: igraph; extra == "misc"
Requires-Dist: leidenalg; extra == "misc"
Requires-Dist: seaborn; extra == "misc"
Requires-Dist: joblib; extra == "misc"
Requires-Dist: jupyterlab; extra == "misc"
Requires-Dist: pot; extra == "misc"
Requires-Dist: memory_profiler; extra == "misc"
Provides-Extra: all
Requires-Dist: piano-integration[misc,rapids,scvi-tools,torch]; extra == "all"
Dynamic: author
Dynamic: home-page
Dynamic: license-file
